thoughtspot_rest_api_v1/__init__.py
thoughtspot_rest_api_v1/_version.py
thoughtspot_rest_api_v1/details_objects.py
thoughtspot_rest_api_v1/tsrestapiv1.py
thoughtspot_rest_api_v1/tsrestapiv2.py
thoughtspot_rest_api_v1-1.8.8.dist-info/METADATA
thoughtspot_rest_api_v1-1.8.8.dist-info/WHEEL
thoughtspot_rest_api_v1-1.8.8.dist-info/top_level.txt
thoughtspot_rest_api_v1-1.8.8.dist-info/RECORD
