Metadata-Version: 2.4
Name: thoughtspot_rest_api_v1
Version: 1.8.8
Summary: Library implementing the ThoughtSpot V1 REST API
Home-page: https://github.com/thoughtspot/thoughtspot_rest_api_v1_python
Author: Bryant Howell
Author-email: bryant.howell@thoughtspot.com
License: MIT
Project-URL: Documentation, https://github.com/thoughtspot/thoughtspot_rest_api_v1_python#readme
Project-URL: Bug Tracker, https://github.com/thoughtspot/thoughtspot_rest_api_v1_python/issues
Classifier: Programming Language :: Python :: 3
Classifier: License :: OSI Approved :: MIT License
Classifier: Operating System :: OS Independent
Requires-Python: >=3.6
Requires-Dist: requests
Requires-Dist: requests_toolbelt
